{"low_leg": {"name": "low", "crossSection": [5, 0.25], "legHeight": 40, "youngModulus": 189000.0, "poissonRatio": 0.27, "density": 7.93e-06, "pulleyRadius": 50, "motorDistanceToCenter": 70, "controlPoint": [[[-30.0, -45.0], 0.1, 90.0], [[-30.0, -30.0], 84.88176347928162, 90.0, 0.1, 270.0], [[36.19188939347467, 19.19282642998192], 48.5554350762461, -48.97482174428526, 58.48912239276922, 131.02517825571476], [[71.0, 25.0], 1.0, 90.0, 28.69685241558644, 270.0], [[71.0, 40.0], 0.1, 90.0]], "nBeams": 20}, "high_leg": {"name": "high", "crossSection": [5, 0.25], "legHeight": 100, "youngModulus": 189000.0, "poissonRatio": 0.27, "density": 7.93e-06, "pulleyRadius": 50, "motorDistanceToCenter": 70, "controlPoint": [[[-30.0, -45.0], 0.1, 90.0], [[-30.0, -30.0], 12.9793185375479, 90.0, 0.1, 270.0], [[29.70198429413401, 2.6339178153975453], 85.03613983904314, -70.9194086336305, 67.01763207505357, 109.0805913663695], [[71.0, 85.0], 0.1, 90.0, 17.62956983944439, 270.0], [[71.0, 100.0], 0.1, 90.0]], "nBeams": 20}, "center_part": {"name": "connector", "density": 1.22e-06, "youngModulus": 35000.0, "poissonRatio": 0.45, "hCrossSection": [5, 0.25], "hDepth": 15, "hThickness": 2.5, "hDiameter": 40, "lCrossSection": [5, 0.25], "lDepth": 15, "lThickness": 2.5, "lDiameter": 40, "height": 60}}