{"low_leg": {"name": "low", "crossSection": [5, 0.5], "legHeight": 80, "youngModulus": 189000.0, "poissonRatio": 0.27, "density": 7.93e-06, "pulleyRadius": 60, "motorDistanceToCenter": 50, "controlPoint": [[[-60.0, -10.0], 0.1, 90.0], [[-60.0, 0.0], 29.204817714345914, 90.0, 0.1, 270.0], [[-24.4872924150485, 53.69751800695363], 18.71852396480004, -37.15599126696944, 71.23613633160937, 142.84400873303056], [[30.0, 55.0], 1.0, 90.0, 49.49542819503472, 270.0], [[30.0, 70.0], 0.1, 90.0]], "nBeams": 30}, "high_leg": {"name": "high", "crossSection": [5, 0.5], "legHeight": 140, "youngModulus": 189000.0, "poissonRatio": 0.27, "density": 7.93e-06, "pulleyRadius": 60, "motorDistanceToCenter": 50, "controlPoint": [[[-60.0, -10.0], 0.1, 90.0], [[-60.0, 0.0], 31.933383562373038, 90.0, 0.1, 270.0], [[9.290938675238166, 79.1524537922849], 15.284406633099136, -57.35921800318172, 41.01795745364636, 122.64078199681826], [[30.0, 115.0], 0.1, 90.0, 50.39114742057012, 270.0], [[30.0, 130.0], 0.1, 90.0]], "nBeams": 30}, "center_part": {"name": "connector", "density": 1.22e-06, "youngModulus": 35000.0, "poissonRatio": 0.45, "hCrossSection": [5, 0.5], "hDepth": 15, "hThickness": 2.5, "hDiameter": 40, "lCrossSection": [5, 0.5], "lDepth": 15, "lThickness": 2.5, "lDiameter": 40, "height": 60}}