{"sLegPt.rL1": 79.98042907623592, "sLegPt.rL2": 54.99514978193076, "sLegPt.x2": 4.319039502245673, "sLegPt.y2": 28.88788313470937, "sLegPt.rA2": -47.117986343375485, "sLegPt.rL3": 69.85885126670513, "lLegPt.rL1": 48.57583574160394, "lLegPt.rL2": 32.30437379774625, "lLegPt.x2": 72.82258333940011, "lLegPt.y2": -7.1352449677658285, "lLegPt.rA2": -63.26473259481744, "lLegPt.rL3": 78.66156630970269, "sLeg.crossSection": [10, 0.5], "sLeg.legHeight": 30, "sLeg.youngModulus": 189000.0, "sLeg.poissonRatio": 0.27, "sLeg.density": 7.93e-06, "sLeg.pulleyRadius": 40, "sLeg.motorDistanceToCenter": 50, "lLeg.crossSection": [10, 0.5], "lLeg.legHeight": 70, "lLeg.youngModulus": 189000.0, "lLeg.poissonRatio": 0.27, "lLeg.density": 7.93e-06, "lLeg.pulleyRadius": 60, "lLeg.motorDistanceToCenter": 50}