{"low_leg": {"name": "sLeg", "crossSection": [10, 2.5], "legHeight": 30, "youngModulus": 189000.0, "poissonRatio": 0.27, "density": 7.93e-06, "pulleyRadius": 40, "motorDistanceToCenter": 50, "controlPoint": [[[-20.0, -45.0], 0.1, 90.0], [[-20.0, -30.0], 62.948044282002755, 90.0, 0.1, 270.0], [[4.3433961541033455, 28.781880393418497], 49.48433287059242, -55.53824074595939], [[71.0, 15.0], 1.0, 90.0, 59.77341539552891, 270.0], [[71.0, 30.0], 0.1, 90.0]], "nBeams": 10}, "high_leg": {"name": "lLeg", "crossSection": [10, 2.5], "legHeight": 90, "youngModulus": 189000.0, "poissonRatio": 0.27, "density": 7.93e-06, "pulleyRadius": 40, "motorDistanceToCenter": 50, "controlPoint": [[[-20.0, -45.0], 0.1, 90.0], [[-20.0, -30.0], 46.40311666600751, 90.0, 0.1, 270.0], [[41.122678504376545, 49.91959999995149], 47.43687997017807, -52.187716818054774], [[71.0, 75.0], 1.0, 90.0, 68.82237440706308, 270.0], [[71.0, 90.0], 0.1, 90.0]], "nBeams": 10}, "center_part": {"name": "connector", "density": 1.22e-06, "youngModulus": 35000.0, "poissonRatio": 0.45, "hCrossSection": [10, 2.5], "hDepth": 15, "hThickness": 2.5, "hDiameter": 40, "lCrossSection": [10, 2.5], "lDepth": 15, "lThickness": 2.5, "lDiameter": 40, "height": 60}}