{"low_leg": {"name": "low", "crossSection": [10, 0.5], "legHeight": 40, "youngModulus": 189000.0, "poissonRatio": 0.27, "density": 7.93e-06, "pulleyRadius": 50, "motorDistanceToCenter": 70, "controlPoint": [[[-30.0, -45.0], 0.1, 90.0], [[-30.0, -30.0], 42.791163909425585, 90.0, 0.1, 270.0], [[29.81499106278055, 41.076586200739335], 54.96226585499143, -42.27717365685372], [[101.0, 25.0], 1.0, 90.0, 66.23592811623325, 270.0], [[101.0, 40.0], 0.1, 90.0]], "nBeams": 20}, "high_leg": {"name": "high", "crossSection": [10, 0.5], "legHeight": 100, "youngModulus": 189000.0, "poissonRatio": 0.27, "density": 7.93e-06, "pulleyRadius": 50, "motorDistanceToCenter": 70, "controlPoint": [[[-30.0, -45.0], 0.1, 90.0], [[-30.0, -30.0], 67.59356115812389, 90.0, 0.1, 270.0], [[17.227647555263612, 43.03981199649968], 50.120813418553034, -34.618844708338635], [[101.0, 85.0], 1.0, 90.0, 38.67538740419732, 270.0], [[101.0, 100.0], 0.1, 90.0]], "nBeams": 20}, "center_part": {"name": "connector", "density": 1.22e-06, "youngModulus": 35000.0, "poissonRatio": 0.45, "hCrossSection": [10, 0.5], "hDepth": 15, "hThickness": 2.5, "hDiameter": 40, "lCrossSection": [10, 0.5], "lDepth": 15, "lThickness": 2.5, "lDiameter": 40, "height": 60}}