{"low_leg": {"name": "low", "crossSection": [5, 0.5], "legHeight": 80, "youngModulus": 189000.0, "poissonRatio": 0.27, "density": 7.93e-06, "pulleyRadius": 60, "motorDistanceToCenter": 50, "controlPoint": [[[-60.0, -10.0], 0.1, 90.0], [[-60.0, 0.0], 34.88392560327752, 90.0, 0.1, 270.0], [[-11.95645303314513, 63.47072810826879], 42.40314625396284, -43.54056831172128, 58.36547137117402, 136.45943168827873], [[30.0, 55.0], 1.0, 90.0, 50.45102570451397, 270.0], [[30.0, 70.0], 0.1, 90.0]], "nBeams": 30}, "high_leg": {"name": "high", "crossSection": [5, 0.5], "legHeight": 140, "youngModulus": 189000.0, "poissonRatio": 0.27, "density": 7.93e-06, "pulleyRadius": 60, "motorDistanceToCenter": 50, "controlPoint": [[[-60.0, -10.0], 0.1, 90.0], [[-60.0, 0.0], 57.593621218285826, 90.0, 0.1, 270.0], [[8.02236112540379, 118.1529275291856], 24.27347016912861, -55.17215887286723, 36.54434430783878, 124.82784112713279], [[30.0, 115.0], 0.1, 90.0, 56.68023248941392, 270.0], [[30.0, 130.0], 0.1, 90.0]], "nBeams": 30}, "center_part": {"name": "connector", "density": 1.22e-06, "youngModulus": 35000.0, "poissonRatio": 0.45, "hCrossSection": [5, 0.5], "hDepth": 15, "hThickness": 2.5, "hDiameter": 40, "lCrossSection": [5, 0.5], "lDepth": 15, "lThickness": 2.5, "lDiameter": 40, "height": 60}}