{"low_leg": {"name": "low", "crossSection": [5, 0.5], "legHeight": 80, "youngModulus": 189000.0, "poissonRatio": 0.27, "density": 7.93e-06, "pulleyRadius": 60, "motorDistanceToCenter": 50, "controlPoint": [[[-60.0, -10.0], 0.1, 90.0], [[-60.0, 0.0], 51.083625674266194, 90.0, 0.1, 270.0], [[-17.35044638964341, 19.472486119685612], 25.493138785306662, -76.6946131549552, 31.90232859467621, 103.3053868450448], [[30.0, 55.0], 1.0, 90.0, 34.68508506006048, 270.0], [[30.0, 70.0], 0.1, 90.0]], "nBeams": 30}, "high_leg": {"name": "high", "crossSection": [5, 0.5], "legHeight": 140, "youngModulus": 189000.0, "poissonRatio": 0.27, "density": 7.93e-06, "pulleyRadius": 60, "motorDistanceToCenter": 50, "controlPoint": [[[-60.0, -10.0], 0.1, 90.0], [[-60.0, 0.0], 27.849597277414134, 90.0, 0.1, 270.0], [[-38.1238729113818, 88.7532753243129], 19.33131194672577, -30.357987847220084, 38.172998971098885, 149.64201215277993], [[30.0, 115.0], 0.1, 90.0, 63.54482607219301, 270.0], [[30.0, 130.0], 0.1, 90.0]], "nBeams": 30}, "center_part": {"name": "connector", "density": 1.22e-06, "youngModulus": 35000.0, "poissonRatio": 0.45, "hCrossSection": [5, 0.5], "hDepth": 15, "hThickness": 2.5, "hDiameter": 40, "lCrossSection": [5, 0.5], "lDepth": 15, "lThickness": 2.5, "lDiameter": 40, "height": 60}}