{"low_leg": {"name": "low", "crossSection": [5, 0.5], "legHeight": 80, "youngModulus": 189000.0, "poissonRatio": 0.27, "density": 7.93e-06, "pulleyRadius": 60, "motorDistanceToCenter": 50, "controlPoint": [[[-60.0, -10.0], 0.1, 90.0], [[-60.0, 0.0], 12.666656720158771, 90.0, 0.1, 270.0], [[-17.3976221626477, 32.75692673875096], 28.658134999565227, -60.32773858947453, 48.87907522296692, 119.6722614105255], [[30.0, 55.0], 1.0, 90.0, 52.40029262741473, 270.0], [[30.0, 70.0], 0.1, 90.0]], "nBeams": 30}, "high_leg": {"name": "high", "crossSection": [5, 0.5], "legHeight": 140, "youngModulus": 189000.0, "poissonRatio": 0.27, "density": 7.93e-06, "pulleyRadius": 60, "motorDistanceToCenter": 50, "controlPoint": [[[-60.0, -10.0], 0.1, 90.0], [[-60.0, 0.0], 37.0543114954357, 90.0, 0.1, 270.0], [[-9.527097346223378, 84.71615550546731], 15.31340832130164, -50.37072448374886, 40.88200629610902, 129.62927551625114], [[30.0, 115.0], 0.1, 90.0, 13.354956909553676, 270.0], [[30.0, 130.0], 0.1, 90.0]], "nBeams": 30}, "center_part": {"name": "connector", "density": 1.22e-06, "youngModulus": 35000.0, "poissonRatio": 0.45, "hCrossSection": [5, 0.5], "hDepth": 15, "hThickness": 2.5, "hDiameter": 40, "lCrossSection": [5, 0.5], "lDepth": 15, "lThickness": 2.5, "lDiameter": 40, "height": 60}}