{"low_leg": {"name": "low", "crossSection": [5, 0.5], "legHeight": 40, "youngModulus": 189000.0, "poissonRatio": 0.27, "density": 7.93e-06, "pulleyRadius": 30, "motorDistanceToCenter": 70, "controlPoint": [[[-10.0, -45.0], 0.1, 90.0], [[-10.0, -30.0], 69.70490079020486, 90.0, 0.1, 270.0], [[34.473701133442255, 19.092348492003033], 54.25042430211336, -71.25139092884437], [[81.0, 25.0], 1.0, 90.0, 46.06993431985468, 270.0], [[81.0, 40.0], 0.1, 90.0]], "nBeams": 20}, "high_leg": {"name": "high", "crossSection": [5, 0.5], "legHeight": 100, "youngModulus": 189000.0, "poissonRatio": 0.27, "density": 7.93e-06, "pulleyRadius": 30, "motorDistanceToCenter": 70, "controlPoint": [[[-10.0, -45.0], 0.1, 90.0], [[-10.0, -30.0], 57.84679744524482, 90.0, 0.1, 270.0], [[51.669328046290296, 73.24461591317682], 37.4306584471384, -26.09198555183159], [[81.0, 85.0], 1.0, 90.0, 47.33014033527441, 270.0], [[81.0, 100.0], 0.1, 90.0]], "nBeams": 20}, "center_part": {"name": "connector", "density": 1.22e-06, "youngModulus": 35000.0, "poissonRatio": 0.45, "hCrossSection": [5, 0.5], "hDepth": 15, "hThickness": 2.5, "hDiameter": 40, "lCrossSection": [5, 0.5], "lDepth": 15, "lThickness": 2.5, "lDiameter": 40, "height": 60}}